{
  "dimensions": {
    "$dimension.x0_5": "2px",
    "$dimension.x1": "4px",
    "$dimension.x1_5": "6px",
    "$dimension.x2": "8px",
    "$dimension.x2_5": "10px",
    "$dimension.x3": "12px",
    "$dimension.x3_5": "14px",
    "$dimension.x4": "16px",
    "$dimension.x4_5": "18px",
    "$dimension.x5": "20px",
    "$dimension.x6": "24px",
    "$dimension.x7": "28px",
    "$dimension.x8": "32px",
    "$dimension.x9": "36px",
    "$dimension.x10": "40px",
    "$dimension.x12": "48px",
    "$dimension.x13": "52px",
    "$dimension.x14": "56px",
    "$dimension.x16": "64px",
    "$dimension.spacing-x.between-chips": "8px",
    "$dimension.spacing-x.global-gutter": "16px",
    "$dimension.spacing-y.component-default": "12px",
    "$dimension.spacing-y.nav-to-title": "20px",
    "$dimension.spacing-y.screen-bottom": "56px",
    "$dimension.spacing-y.between-text": "6px",
    "$font-size.t1": "0.6875rem",
    "$font-size.t2": "0.75rem",
    "$font-size.t3": "0.8125rem",
    "$font-size.t4": "0.875rem",
    "$font-size.t5": "1rem",
    "$font-size.t6": "1.125rem",
    "$font-size.t7": "1.25rem",
    "$font-size.t8": "1.375rem",
    "$font-size.t9": "1.5rem",
    "$font-size.t10": "1.625rem",
    "$font-size.t1-static": "11px",
    "$font-size.t2-static": "12px",
    "$font-size.t3-static": "13px",
    "$font-size.t4-static": "14px",
    "$font-size.t5-static": "16px",
    "$font-size.t6-static": "18px",
    "$font-size.t7-static": "20px",
    "$font-size.t8-static": "22px",
    "$font-size.t9-static": "24px",
    "$font-size.t10-static": "26px",
    "$line-height.t1": "0.9375rem",
    "$line-height.t2": "1rem",
    "$line-height.t3": "1.125rem",
    "$line-height.t4": "1.1875rem",
    "$line-height.t5": "1.375rem",
    "$line-height.t6": "1.5rem",
    "$line-height.t7": "1.6875rem",
    "$line-height.t8": "1.875rem",
    "$line-height.t9": "2rem",
    "$line-height.t10": "2.1875rem",
    "$line-height.t1-static": "15px",
    "$line-height.t2-static": "16px",
    "$line-height.t3-static": "18px",
    "$line-height.t4-static": "19px",
    "$line-height.t5-static": "22px",
    "$line-height.t6-static": "24px",
    "$line-height.t7-static": "27px",
    "$line-height.t8-static": "30px",
    "$line-height.t9-static": "32px",
    "$line-height.t10-static": "35px",
    "$radius.r0_5": "2px",
    "$radius.r1": "4px",
    "$radius.r1_5": "6px",
    "$radius.r2": "8px",
    "$radius.r2_5": "10px",
    "$radius.r3": "12px",
    "$radius.r3_5": "14px",
    "$radius.r4": "16px",
    "$radius.r5": "20px",
    "$radius.r6": "24px",
    "$radius.full": "9999px"
  }
}
